pycolourslib/__init__.py
pycolourslib/colours.py
pycolourslib-1.0.dist-info/METADATA
pycolourslib-1.0.dist-info/WHEEL
pycolourslib-1.0.dist-info/top_level.txt
pycolourslib-1.0.dist-info/RECORD
