Metadata-Version: 2.1
Name: pycolourslib
Version: 1.0
Summary: a python module with variabled colours for more simplicity and less time-wasting in your projects
Home-page: https://github.com/KZed-K/pycolourslib
Author: QZ-K
Author-email: kuzeykural040510@gmail.com
Classifier: Programming Language :: Python :: 3
Classifier: License :: OSI Approved :: MIT License
Classifier: Operating System :: OS Independent
Requires-Python: >=3.6
